liana_rpc/__init__.py
liana_rpc/liana_rpc.py
liana_rpc/utils/__init__.py
liana_rpc/utils/rpc.py
liana_rpc-0.0.3.dist-info/LICENCE
liana_rpc-0.0.3.dist-info/METADATA
liana_rpc-0.0.3.dist-info/WHEEL
liana_rpc-0.0.3.dist-info/top_level.txt
liana_rpc-0.0.3.dist-info/RECORD
